LICENSE
MANIFEST.in
README.md
setup.py
EastPlus/__init__.py
EastPlus/__version__.py
EastPlus/cffex_data.py
EastPlus/demo.py
EastPlus/east_data.py
EastPlus/test.py
EastPlus/tool.py
EastPlus/toolbox.py
EastPlus.egg-info/PKG-INFO
EastPlus.egg-info/SOURCES.txt
EastPlus.egg-info/dependency_links.txt
EastPlus.egg-info/top_level.txt