Metadata-Version: 2.1
Name: EastPlus
Version: 0.3.3
Summary: My short description for my project.
Home-page: https://github.com/liufeng3486/EastPlus.git
Author: Adol liu
Author-email: 34862933@qq.com
License: MIT
Classifier: License :: OSI Approved :: MIT License
Classifier: Programming Language :: Python
Classifier: Programming Language :: Python :: 3
Classifier: Programming Language :: Python :: 3.6
Classifier: Programming Language :: Python :: Implementation :: CPython
Classifier: Programming Language :: Python :: Implementation :: PyPy
Requires-Python: >=3.6.0
License-File: LICENSE
